README.rst
delfick_app.py
setup.py
delfick_app.egg-info/PKG-INFO
delfick_app.egg-info/SOURCES.txt
delfick_app.egg-info/dependency_links.txt
delfick_app.egg-info/requires.txt
delfick_app.egg-info/top_level.txt