Metadata-Version: 1.0
Name: delfick-app
Version: 0.9.6
Summary: Customized App mainline helper
Home-page: http://github.com/delfick/delfick_app
Author: Stephen Moore
Author-email: stephen@delfick.com
License: MIT
Platform: UNKNOWN
